dlc2kinematics/__init__.py
dlc2kinematics/_version.py
dlc2kinematics/joint_analysis.py
dlc2kinematics/mainfxns.py
dlc2kinematics/plotting.py
dlc2kinematics/preprocess.py
dlc2kinematics/preprocess_c3d.py
dlc2kinematics/quaternions.py
dlc2kinematics/version.py
dlc2kinematics/visualization.py
dlc2kinematics/_tests/_init_.py
dlc2kinematics/_tests/test_reader.py
dlc2kinematics/utils/__init__.py
dlc2kinematics/utils/auxiliaryfunctions.py
dlc2kinematics-0.0.7.dist-info/LICENSE
dlc2kinematics-0.0.7.dist-info/METADATA
dlc2kinematics-0.0.7.dist-info/WHEEL
dlc2kinematics-0.0.7.dist-info/entry_points.txt
dlc2kinematics-0.0.7.dist-info/top_level.txt
dlc2kinematics-0.0.7.dist-info/RECORD
