Metadata-Version: 2.1
Name: dlc2kinematics
Version: 0.0.7
Summary: Library for kinematic analysis of DeepLabCut outputs
Home-page: https://github.com/AdaptiveMotorControlLab/dlc2kinematics/
Author: Mackenzie Mathis Lab Members
Author-email: mackenzie@post.harvard.edu
License: custom
Project-URL: Bug Tracker, https://github.com/AdaptiveMotorControlLab/DLC2Kinematics/issues
Project-URL: Documentation, https://github.com/AdaptiveMotorControlLab/DLC2Kinematics
Project-URL: Source Code, https://github.com/AdaptiveMotorControlLab/DLC2Kinematics
Project-URL: User Support, https://github.com/AdaptiveMotorControlLab/DLC2Kinematics/issues
Classifier: Programming Language :: Python :: 3
Classifier: Operating System :: OS Independent
Requires-Python: >=3.8
License-File: LICENSE
Requires-Dist: h5py
Requires-Dist: c3d
Requires-Dist: ipython
Requires-Dist: ipython-genutils
Requires-Dist: matplotlib (>=3.0.3)
Requires-Dist: numpy (<1.25)
Requires-Dist: pandas (>=1.0)
Requires-Dist: python-dateutil
Requires-Dist: pyyaml
Requires-Dist: requests
Requires-Dist: setuptools
Requires-Dist: scikit-image
Requires-Dist: scikit-learn (<1.2.2)
Requires-Dist: scikit-kinematics
Requires-Dist: scipy
Requires-Dist: tables
Requires-Dist: umap-learn
Requires-Dist: tqdm
Requires-Dist: ruamel.yaml (>=0.15.0)
Requires-Dist: wheel
Provides-Extra: testing
Requires-Dist: pytest ; extra == 'testing'
Requires-Dist: pytest-cov ; extra == 'testing'
Requires-Dist: tox ; extra == 'testing'
